{
  "parent": "minecraft:recipes/root",
  "rewards": {
    "recipes": [
      "undergarden:depthrock_tile_slab"
    ]
  },
  "criteria": {
    "has_depthrock_tiles": {
      "trigger": "minecraft:inventory_changed",
      "conditions": {
        "items": [
          {
            "items": [
              "undergarden:depthrock_tiles"
            ]
          }
        ]
      }
    },
    "has_the_recipe": {
      "trigger": "minecraft:recipe_unlocked",
      "conditions": {
        "recipe": "undergarden:depthrock_tile_slab"
      }
    }
  },
  "requirements": [
    [
      "has_depthrock_tiles",
      "has_the_recipe"
    ]
  ]
}