{
  "parent": "undergarden:undergarden/catalyst",
  "display": {
    "icon": {
      "item": "undergarden:deepturf_block"
    },
    "title": {
      "translate": "advancement.undergarden.enter_undergarden.title"
    },
    "description": {
      "translate": "advancement.undergarden.enter_undergarden.desc"
    },
    "frame": "task",
    "show_toast": true,
    "announce_to_chat": true,
    "hidden": false
  },
  "criteria": {
    "enter_undergarden": {
      "trigger": "minecraft:changed_dimension",
      "conditions": {
        "to": "undergarden:undergarden"
      }
    }
  },
  "requirements": [
    [
      "enter_undergarden"
    ]
  ]
}